diffusionui/__init__.py
diffusionui/__version__.py
diffusionui/cli.py
diffusionui/gradio_interface.py
diffusionui/py.typed
diffusionui/pipelines/README.md
diffusionui/pipelines/__init__.py
diffusionui/pipelines/pipeline_stable_diffusion.py
diffusionui-0.4.1.dist-info/LICENSE
diffusionui-0.4.1.dist-info/METADATA
diffusionui-0.4.1.dist-info/WHEEL
diffusionui-0.4.1.dist-info/entry_points.txt
diffusionui-0.4.1.dist-info/top_level.txt
diffusionui-0.4.1.dist-info/RECORD
