Metadata-Version: 2.1
Name: diffusionui
Version: 0.4.1
Summary: Unified Stable Diffusion pipeline for diffusers
Home-page: https://github.com/leszekhanusz/diffusion-ui-backend
Author: Leszek Hanusz
Author-email: leszek.hanusz@gmail.com
License: Apache
Keywords: diffusers stable-diffusion
Platform: any
Classifier: Development Status :: 5 - Production/Stable
Classifier: Intended Audience :: Developers
Classifier: Intended Audience :: Science/Research
Classifier: License :: OSI Approved :: Apache Software License
Classifier: Topic :: Scientific/Engineering :: Artificial Intelligence
Classifier: Operating System :: OS Independent
Classifier: Programming Language :: Python :: 3
Classifier: Programming Language :: Python :: 3 :: Only
Classifier: Programming Language :: Python :: 3.6
Classifier: Programming Language :: Python :: 3.7
Classifier: Programming Language :: Python :: 3.8
Classifier: Programming Language :: Python :: 3.9
Classifier: Programming Language :: Python :: 3.10
Requires-Python: >=3.6.0
Requires-Dist: diffusers (==0.4.2)
Requires-Dist: gradio (>=3.1.6)
Requires-Dist: transformers (>=4.21.3)
Provides-Extra: dev
Requires-Dist: black (==22.3.0) ; extra == 'dev'
Requires-Dist: check-manifest (<1,>=0.42) ; extra == 'dev'
Requires-Dist: sphinx (<6,>=5.1.1) ; extra == 'dev'
Requires-Dist: sphinx-rtd-theme (==1.0.0) ; extra == 'dev'
Requires-Dist: sphinx-tabs (==3.4.0) ; extra == 'dev'
Requires-Dist: flake8 (==3.8.1) ; extra == 'dev'
Requires-Dist: isort (==5.10.1) ; extra == 'dev'
